<?xml version='1.0'?>
<ns2:test-suite xmlns:ns2='urn:model.allure.qatools.yandex.ru' start='1588575643344' stop='1588575951826'>
    <name>5 major hosts:</name>
    <title>5 major hosts:</title>
    <test-cases>
        <test-case start='1588575643360' status='passed' stop='1588575795152'>
            <name>Test transition to payment on CheckMyPersonalStatement.net</name>
            <title>Test transition to payment on CheckMyPersonalStatement.net</title>
            <labels/>
            <parameters/>
            <steps>
                <step start='1588575647712' status='passed' stop='1588575763831'>
                    <name>I am on page "https://www.checkmypersonalstatement.net/order?EssayForm[instruction]=Test%20order&amp;EssayForm[first_name]=Test&amp;EssayForm[email]=sergei_melnichuk@govitall.com&amp;EssayForm[phone]=11111111111111"</name>
                    <title>I am on page "https://www.checkmypersonalstatement.net/order?EssayForm[instruction]=Test%20order&amp;EssayForm[first_name]=Test&amp;EssayForm[email]=sergei_melnichuk@govitall.com&amp;EssayForm[phone]=11111111111111"</title>
                    <attachments/>
                    <steps/>
                </step>
                <step start='1588575763831' status='passed' stop='1588575764508'>
                    <name>I wait for element "#essayform-terms", 100</name>
                    <title>I wait for element "#essayform-terms", 100</title>
                    <attachments/>
                    <steps/>
                </step>
                <step start='1588575764509' status='passed' stop='1588575765306'>
                    <name>I click "#essayform-terms"</name>
                    <title>I click "#essayform-terms"</title>
                    <attachments/>
                    <steps/>
                </step>
                <step start='1588575765306' status='passed' stop='1588575766129'>
                    <name>I click "//*[@id="orderForm"]/div[2]/div[3]/div[2]/div[2]/button"</name>
                    <title>I click "//*[@id="orderForm"]/div[2]/div[3]/div[2]/div[2]/button"</title>
                    <attachments/>
                    <steps/>
                </step>
                <step start='1588575766129' status='passed' stop='1588575792199'>
                    <name>I wait for element "//*[@id="checkout_wrapper"]/div[1]/div/div/div[1]/img", 100</name>
                    <title>I wait for element "//*[@id="checkout_wrapper"]/div[1]/div/div/div[1]/img", 100</title>
                    <attachments/>
                    <steps/>
                </step>
                <step start='1588575792199' status='passed' stop='1588575795149'>
                    <name>I see element "//*[@id="checkout_wrapper"]/div[1]/div/div/div[1]/img"</name>
                    <title>I see element "//*[@id="checkout_wrapper"]/div[1]/div/div/div[1]/img"</title>
                    <attachments/>
                    <steps/>
                </step>
            </steps>
            <attachments/>
        </test-case>
        <test-case start='1588575795960' status='passed' stop='1588575843932'>
            <name>Test transition to payment on LoRService.com</name>
            <title>Test transition to payment on LoRService.com</title>
            <labels/>
            <parameters/>
            <steps>
                <step start='1588575797071' status='passed' stop='1588575813169'>
                    <name>I am on page "https://www.lorservice.com/order?EssayForm[instruction]=Test%20order&amp;EssayForm[first_name]=Test&amp;EssayForm[email]=sergei_melnichuk@govitall.com&amp;EssayForm[phone]=11111111111111"</name>
                    <title>I am on page "https://www.lorservice.com/order?EssayForm[instruction]=Test%20order&amp;EssayForm[first_name]=Test&amp;EssayForm[email]=sergei_melnichuk@govitall.com&amp;EssayForm[phone]=11111111111111"</title>
                    <attachments/>
                    <steps/>
                </step>
                <step start='1588575813169' status='passed' stop='1588575813831'>
                    <name>I wait for element "#essayform-terms", 100</name>
                    <title>I wait for element "#essayform-terms", 100</title>
                    <attachments/>
                    <steps/>
                </step>
                <step start='1588575813831' status='passed' stop='1588575814674'>
                    <name>I click "#essayform-terms"</name>
                    <title>I click "#essayform-terms"</title>
                    <attachments/>
                    <steps/>
                </step>
                <step start='1588575814675' status='passed' stop='1588575815511'>
                    <name>I click "//*[@id="orderForm"]/div[2]/div[3]/div[2]/div[2]/button"</name>
                    <title>I click "//*[@id="orderForm"]/div[2]/div[3]/div[2]/div[2]/button"</title>
                    <attachments/>
                    <steps/>
                </step>
                <step start='1588575815511' status='passed' stop='1588575843303'>
                    <name>I wait for element "//*[@id="checkout_wrapper"]/div[1]/div/div/div[1]/img", 100</name>
                    <title>I wait for element "//*[@id="checkout_wrapper"]/div[1]/div/div/div[1]/img", 100</title>
                    <attachments/>
                    <steps/>
                </step>
                <step start='1588575843303' status='passed' stop='1588575843931'>
                    <name>I see element "//*[@id="checkout_wrapper"]/div[1]/div/div/div[1]/img"</name>
                    <title>I see element "//*[@id="checkout_wrapper"]/div[1]/div/div/div[1]/img"</title>
                    <attachments/>
                    <steps/>
                </step>
            </steps>
            <attachments/>
        </test-case>
        <test-case start='1588575844395' status='passed' stop='1588575884345'>
            <name>Test transition to payment on PersonalStatementWritingServices.net</name>
            <title>Test transition to payment on PersonalStatementWritingServices.net</title>
            <labels/>
            <parameters/>
            <steps>
                <step start='1588575845586' status='passed' stop='1588575869760'>
                    <name>I am on page "https://www.personalstatementwritingservices.net/order?EssayForm[instruction]=Test%20order&amp;EssayForm[first_name]=Test&amp;EssayForm[email]=sergei_melnichuk@govitall.com&amp;EssayForm[phone]=11111111111111"</name>
                    <title>I am on page "https://www.personalstatementwritingservices.net/order?EssayForm[instruction]=Test%20order&amp;EssayForm[first_name]=Test&amp;EssayForm[email]=sergei_melnichuk@govitall.com&amp;EssayForm[phone]=11111111111111"</title>
                    <attachments/>
                    <steps/>
                </step>
                <step start='1588575869760' status='passed' stop='1588575870397'>
                    <name>I wait for element "#essayform-terms", 100</name>
                    <title>I wait for element "#essayform-terms", 100</title>
                    <attachments/>
                    <steps/>
                </step>
                <step start='1588575870398' status='passed' stop='1588575871313'>
                    <name>I click "#essayform-terms"</name>
                    <title>I click "#essayform-terms"</title>
                    <attachments/>
                    <steps/>
                </step>
                <step start='1588575871313' status='passed' stop='1588575872162'>
                    <name>I click "//*[@id="orderForm"]/div[2]/div[3]/div[2]/div[2]/button"</name>
                    <title>I click "//*[@id="orderForm"]/div[2]/div[3]/div[2]/div[2]/button"</title>
                    <attachments/>
                    <steps/>
                </step>
                <step start='1588575872162' status='passed' stop='1588575882662'>
                    <name>I wait for element "//*[@id="checkout_wrapper"]/div[1]/div/div/div[1]/img", 100</name>
                    <title>I wait for element "//*[@id="checkout_wrapper"]/div[1]/div/div/div[1]/img", 100</title>
                    <attachments/>
                    <steps/>
                </step>
                <step start='1588575882663' status='passed' stop='1588575884344'>
                    <name>I see element "//*[@id="checkout_wrapper"]/div[1]/div/div/div[1]/img"</name>
                    <title>I see element "//*[@id="checkout_wrapper"]/div[1]/div/div/div[1]/img"</title>
                    <attachments/>
                    <steps/>
                </step>
            </steps>
            <attachments/>
        </test-case>
        <test-case start='1588575884896' status='passed' stop='1588575913748'>
            <name>Test transition to payment on SoPServices.net</name>
            <title>Test transition to payment on SoPServices.net</title>
            <labels/>
            <parameters/>
            <steps>
                <step start='1588575886010' status='passed' stop='1588575900817'>
                    <name>I am on page "https://www.sopservices.net/order?EssayForm[instruction]=Test%20order&amp;EssayForm[first_name]=Test&amp;EssayForm[email]=sergei_melnichuk@govitall.com&amp;EssayForm[phone]=11111111111111"</name>
                    <title>I am on page "https://www.sopservices.net/order?EssayForm[instruction]=Test%20order&amp;EssayForm[first_name]=Test&amp;EssayForm[email]=sergei_melnichuk@govitall.com&amp;EssayForm[phone]=11111111111111"</title>
                    <attachments/>
                    <steps/>
                </step>
                <step start='1588575900817' status='passed' stop='1588575901773'>
                    <name>I wait for element "#essayform-terms", 100</name>
                    <title>I wait for element "#essayform-terms", 100</title>
                    <attachments/>
                    <steps/>
                </step>
                <step start='1588575901773' status='passed' stop='1588575902623'>
                    <name>I click "#essayform-terms"</name>
                    <title>I click "#essayform-terms"</title>
                    <attachments/>
                    <steps/>
                </step>
                <step start='1588575902623' status='passed' stop='1588575903404'>
                    <name>I click "//*[@id="orderForm"]/div[2]/div[3]/div[2]/div[2]/button"</name>
                    <title>I click "//*[@id="orderForm"]/div[2]/div[3]/div[2]/div[2]/button"</title>
                    <attachments/>
                    <steps/>
                </step>
                <step start='1588575903404' status='passed' stop='1588575912653'>
                    <name>I wait for element "//*[@id="checkout_wrapper"]/div[1]/div/div/div[1]/img", 100</name>
                    <title>I wait for element "//*[@id="checkout_wrapper"]/div[1]/div/div/div[1]/img", 100</title>
                    <attachments/>
                    <steps/>
                </step>
                <step start='1588575912653' status='passed' stop='1588575913747'>
                    <name>I see element "//*[@id="checkout_wrapper"]/div[1]/div/div/div[1]/img"</name>
                    <title>I see element "//*[@id="checkout_wrapper"]/div[1]/div/div/div[1]/img"</title>
                    <attachments/>
                    <steps/>
                </step>
            </steps>
            <attachments/>
        </test-case>
        <test-case start='1588575914253' status='passed' stop='1588575951254'>
            <name>Test transition to payment on ResidencyPersonalStatements.net</name>
            <title>Test transition to payment on ResidencyPersonalStatements.net</title>
            <labels/>
            <parameters/>
            <steps>
                <step start='1588575915359' status='passed' stop='1588575934773'>
                    <name>I am on page "https://residencypersonalstatements.net/order?EssayForm[instruction]=Test%20order&amp;EssayForm[first_name]=Test&amp;EssayForm[email]=sergei_melnichuk@govitall.com&amp;EssayForm[phone]=11111111111111"</name>
                    <title>I am on page "https://residencypersonalstatements.net/order?EssayForm[instruction]=Test%20order&amp;EssayForm[first_name]=Test&amp;EssayForm[email]=sergei_melnichuk@govitall.com&amp;EssayForm[phone]=11111111111111"</title>
                    <attachments/>
                    <steps/>
                </step>
                <step start='1588575934773' status='passed' stop='1588575935507'>
                    <name>I wait for element "#essayform-terms", 100</name>
                    <title>I wait for element "#essayform-terms", 100</title>
                    <attachments/>
                    <steps/>
                </step>
                <step start='1588575935508' status='passed' stop='1588575937091'>
                    <name>I click "#essayform-terms"</name>
                    <title>I click "#essayform-terms"</title>
                    <attachments/>
                    <steps/>
                </step>
                <step start='1588575937091' status='passed' stop='1588575937944'>
                    <name>I click "//*[@id="orderForm"]/div[2]/div[6]/div[3]/button"</name>
                    <title>I click "//*[@id="orderForm"]/div[2]/div[6]/div[3]/button"</title>
                    <attachments/>
                    <steps/>
                </step>
                <step start='1588575937945' status='passed' stop='1588575948401'>
                    <name>I wait for element "//*[@id="checkout_wrapper"]/div[1]/div/div/div[1]/img", 100</name>
                    <title>I wait for element "//*[@id="checkout_wrapper"]/div[1]/div/div/div[1]/img", 100</title>
                    <attachments/>
                    <steps/>
                </step>
                <step start='1588575948402' status='passed' stop='1588575951253'>
                    <name>I see element "//*[@id="checkout_wrapper"]/div[1]/div/div/div[1]/img"</name>
                    <title>I see element "//*[@id="checkout_wrapper"]/div[1]/div/div/div[1]/img"</title>
                    <attachments/>
                    <steps/>
                </step>
            </steps>
            <attachments/>
        </test-case>
    </test-cases>
</ns2:test-suite>